ptws/__init__.py
ptws-0.0.1.dist-info/licenses/LICENSE
ptws-0.0.1.dist-info/METADATA
ptws-0.0.1.dist-info/WHEEL
ptws-0.0.1.dist-info/top_level.txt
ptws-0.0.1.dist-info/RECORD
