Metadata-Version: 2.4
Name: ptws
Version: 0.0.1
Summary: Official placeholder for the PenTest.WS Python packages. Reserved by PenTest.WS.
Author-email: "PenTest.WS" <support@pentest.ws>
Project-URL: Homepage, https://pentest.ws
Project-URL: Source, https://github.com/PenTestWS
Keywords: pentest,security,automation,ptws
Classifier: Programming Language :: Python :: 3
Classifier: License :: OSI Approved :: MIT License
Classifier: Development Status :: 3 - Alpha
Classifier: Intended Audience :: Information Technology
Classifier: Topic :: Security
Requires-Python: >=3.10
License-File: LICENSE
Dynamic: license-file
